dowker_rips_complex-2.0.0.dist-info/licenses/LICENSE
drc/__init__.py
drc/dowker_rips_complex.py
dowker_rips_complex-2.0.0.dist-info/METADATA
dowker_rips_complex-2.0.0.dist-info/WHEEL
dowker_rips_complex-2.0.0.dist-info/top_level.txt
dowker_rips_complex-2.0.0.dist-info/RECORD
