Metadata-Version: 2.4
Name: dowker-rips-complex
Version: 2.0.0
Summary: Implementation of the Dowker-Rips complex.
Author: m-a-huber
License-Expression: MIT
Project-URL: Homepage, https://github.com/m-a-huber/dowker-rips-complex
Project-URL: Issues, https://github.com/m-a-huber/dowker-rips-complex/issues
Requires-Python: >=3.10
License-File: LICENSE
Requires-Dist: giotto-ph>=0.2.4
Requires-Dist: numba>=0.61.2
Requires-Dist: numpy>=2.2.6
Requires-Dist: scikit-learn>=1.7.1
Dynamic: license-file
